sixma/__init__.py
sixma/core.py
sixma/generators.py
sixma-0.4.0.dist-info/METADATA
sixma-0.4.0.dist-info/WHEEL
sixma-0.4.0.dist-info/RECORD
