Metadata-Version: 2.4
Name: sixma
Version: 0.4.0
Summary: Add your description here
Author-email: Alejandro Piad <apiad@apiad.net>
Classifier: License :: OSI Approved :: MIT License
Classifier: Operating System :: OS Independent
Classifier: Programming Language :: Python :: 3.12
Requires-Python: >=3.12
